openg2p_spar_mapper_api/__init__.py
openg2p_spar_mapper_api/app.py
openg2p_spar_mapper_api/config.py
openg2p_spar_mapper_api/controllers/__init__.py
openg2p_spar_mapper_api/controllers/async_mapper_controller.py
openg2p_spar_mapper_api/controllers/sync_mapper_controller.py
openg2p_spar_mapper_api/errors/__init__.py
openg2p_spar_mapper_api/errors/error_codes.py
openg2p_spar_mapper_api/models/__init__.py
openg2p_spar_mapper_api/models/id_fa_mapping.py
openg2p_spar_mapper_api/schemas/__init__.py
openg2p_spar_mapper_api/services/__init__.py
openg2p_spar_mapper_api/services/exceptions.py
openg2p_spar_mapper_api/services/id_fa_mapping_validations.py
openg2p_spar_mapper_api/services/mapper.py
openg2p_spar_mapper_api/services/request_helper.py
openg2p_spar_mapper_api/services/request_validations.py
openg2p_spar_mapper_api/services/response_helper.py
openg2p_spar_mapper_api/services/session_service.py
openg2p_spar_mapper_api-1.1.0.dist-info/METADATA
openg2p_spar_mapper_api-1.1.0.dist-info/WHEEL
openg2p_spar_mapper_api-1.1.0.dist-info/licenses/LICENSE
openg2p_spar_mapper_api-1.1.0.dist-info/RECORD
