Metadata-Version: 2.4
Name: openg2p-spar-mapper-api
Version: 1.1.0
Summary: SPAR Mapper compliant with G2P Connect APIs
Project-URL: Homepage, https://openg2p.org
Project-URL: Documentation, https://docs.openg2p.org/
Project-URL: Repository, https://github.com/OpenG2P/openg2p-spar-mapper-api
Project-URL: Source, https://github.com/OpenG2P/openg2p-spar-mapper-api
Author-email: OpenG2P <info@openg2p.org>
License-File: LICENSE
Classifier: License :: OSI Approved :: Mozilla Public License 2.0 (MPL 2.0)
Classifier: Operating System :: OS Independent
Classifier: Programming Language :: Python :: 3
Requires-Python: >=3.7
Requires-Dist: asyncpg
Requires-Dist: gunicorn~=22.0.0
Requires-Dist: openg2p-fastapi-common~=1.1.2
Requires-Dist: openg2p-g2pconnect-common-lib
Requires-Dist: openg2p-g2pconnect-mapper-lib
Requires-Dist: psycopg2
